smartjs/__init__.py
smartjs/base.py
smartjs/collection.py
smartjs/constants.py
smartjs/elements.py
smartjs/functions.py
smartjs/javascript.py
smartjs/page.py
smartjs/path.py
smartjs/style.py
smartjs-0.1.6.dist-info/WHEEL
smartjs-0.1.6.dist-info/METADATA
smartjs-0.1.6.dist-info/RECORD
